corpus_toolkit/__init__.py
corpus_toolkit/antbnc_lemmas_ver_003.txt
corpus_toolkit/corpus_toolkit.py
corpus_toolkit/corpus_tools.py
corpus_toolkit_dev/__init__.py
corpus_toolkit_dev/corpus_toolkit.py
corpus_toolkit_dev/corpus_tools.py
corpus_toolkit-0.32.dist-info/METADATA
corpus_toolkit-0.32.dist-info/WHEEL
corpus_toolkit-0.32.dist-info/top_level.txt
corpus_toolkit-0.32.dist-info/RECORD
