Metadata-Version: 2.1
Name: corpus_toolkit
Version: 0.32
Summary: A simple Python toolkit for corpus analyses
Home-page: https://kristopherkyle.github.io/corpus_toolkit/
Author: Kristopher Kyle
Author-email: kristopherkyle1@gmail.com
License: UNKNOWN
Platform: UNKNOWN
Classifier: Programming Language :: Python :: 3
Classifier: License :: OSI Approved :: MIT License
Classifier: Operating System :: OS Independent
